python_slimta_redisstorage-0.3.0-py2.7-nspkg.pth
python_slimta_redisstorage-0.3.0.dist-info/DESCRIPTION.rst
python_slimta_redisstorage-0.3.0.dist-info/METADATA
python_slimta_redisstorage-0.3.0.dist-info/RECORD
python_slimta_redisstorage-0.3.0.dist-info/WHEEL
python_slimta_redisstorage-0.3.0.dist-info/metadata.json
python_slimta_redisstorage-0.3.0.dist-info/namespace_packages.txt
python_slimta_redisstorage-0.3.0.dist-info/top_level.txt
slimta/redisstorage/__init__.py
