Metadata-Version: 2.0
Name: python-slimta-redisstorage
Version: 0.3.0
Summary: Adds a redis-based queue extension to python-slimta.
Home-page: http://slimta.org/
Author: Ian Good
Author-email: icgood@gmail.com
License: MIT
Platform: UNKNOWN
Classifier: Development Status :: 3 - Alpha
Classifier: Topic :: Communications :: Email :: Mail Transport Agents
Classifier: Intended Audience :: Developers
Classifier: Intended Audience :: Information Technology
Classifier: License :: OSI Approved :: MIT License
Classifier: Programming Language :: Python
Classifier: Programming Language :: Python :: 2.7
Classifier: Programming Language :: Python :: 3.3
Classifier: Programming Language :: Python :: 3.4
Classifier: Programming Language :: Python :: 3.5
Requires-Dist: python-slimta (>=3.0)
Requires-Dist: redis
Requires-Dist: six (>=1)
